django_plugin_system/__init__.py
django_plugin_system/admin.py
django_plugin_system/apps.py
django_plugin_system/helpers.py
django_plugin_system/models.py
django_plugin_system/register.py
django_plugin_system/signals.py
django_plugin_system/storage.py
django_plugin_system/management/__init__.py
django_plugin_system/management/commands/__init__.py
django_plugin_system/management/commands/pluginsync.py
django_plugin_system/services/__init__.py
django_plugin_system/services/sync.py
django_plugin_system-1.1.0.dist-info/licenses/LICENSE
django_plugin_system-1.1.0.dist-info/METADATA
django_plugin_system-1.1.0.dist-info/WHEEL
django_plugin_system-1.1.0.dist-info/top_level.txt
django_plugin_system-1.1.0.dist-info/RECORD
