Metadata-Version: 2.4
Name: django-plugin-system
Version: 1.1.0
Summary: A lightweight plugin registry for Django with admin management and registry→DB sync.
Author-email: Alireza Tabatabaeian <alireza.tabatabaeian@gmail.com>
Project-URL: Homepage, https://github.com/Alireza-Tabatabaeian/django-plugin-system
Project-URL: Issues, https://github.com/Alireza-Tabatabaeian/django-plugin-system/issues
Keywords: django,plugins,registry,otp,extensibility
Classifier: Development Status :: 3 - Alpha
Classifier: Environment :: Web Environment
Classifier: Framework :: Django
Classifier: Framework :: Django :: 4.2
Classifier: Framework :: Django :: 5.0
Classifier: Intended Audience :: Developers
Classifier: License :: OSI Approved :: MIT License
Classifier: Programming Language :: Python
Classifier: Programming Language :: Python :: 3
Classifier: Programming Language :: Python :: 3.10
Classifier: Programming Language :: Python :: 3.11
Classifier: Programming Language :: Python :: 3.12
Classifier: Topic :: Software Development :: Libraries :: Application Frameworks
Classifier: Topic :: Internet :: WWW/HTTP
Requires-Python: >=3.10
License-File: LICENSE
Requires-Dist: Django>=4.2
Provides-Extra: dev
Requires-Dist: pytest>=8; extra == "dev"
Requires-Dist: pytest-django>=4.8.0; extra == "dev"
Requires-Dist: mypy>=1.8; extra == "dev"
Requires-Dist: django-stubs>=5.0.0; extra == "dev"
Requires-Dist: black>=24.0.0; extra == "dev"
Requires-Dist: ruff>=0.5.0; extra == "dev"
Dynamic: license-file
